realesrgan_ncnn_py-2.0.0.dist-info/METADATA
realesrgan_ncnn_py-2.0.0.dist-info/WHEEL
realesrgan_ncnn_py-2.0.0.dist-info/licenses/LICENSE
realesrgan_ncnn_py/__init__.py
realesrgan_ncnn_py/models/realesr-animevideov3-x2.bin
realesrgan_ncnn_py/models/realesr-animevideov3-x2.param
realesrgan_ncnn_py/models/realesr-animevideov3-x3.bin
realesrgan_ncnn_py/models/realesr-animevideov3-x3.param
realesrgan_ncnn_py/models/realesr-animevideov3-x4.bin
realesrgan_ncnn_py/models/realesr-animevideov3-x4.param
realesrgan_ncnn_py/models/realesrgan-x4plus-anime.bin
realesrgan_ncnn_py/models/realesrgan-x4plus-anime.param
realesrgan_ncnn_py/models/realesrgan-x4plus.bin
realesrgan_ncnn_py/models/realesrgan-x4plus.param
realesrgan_ncnn_py/realesrgan_ncnn_vulkan.py
realesrgan_ncnn_py/realesrgan_ncnn_vulkan_wrapper.cpython-39-darwin.so
realesrgan_ncnn_py-2.0.0.dist-info/RECORD
